pytoolmaster/__init__.py
pytoolmaster/brainy_math.py
pytoolmaster/error_handler_pro.py
pytoolmaster/imageify_cli.py
pytoolmaster/task_flow.py
pytoolmaster/text_summarizr.py
pytoolmaster/utils.py
pytoolmaster-1.0.0.dist-info/LICENSE
pytoolmaster-1.0.0.dist-info/METADATA
pytoolmaster-1.0.0.dist-info/WHEEL
pytoolmaster-1.0.0.dist-info/top_level.txt
pytoolmaster-1.0.0.dist-info/RECORD
