Metadata-Version: 2.2
Name: PyToolMaster
Version: 1.0.0
Summary: A Swiss Army knife for developers with text summarization, ASCII art, task automation, math tools, and error handling.
Home-page: https://github.com/shiboshreeroy/PyToolMaster
Author: Shiboshree Roy
Author-email: shiboshreeroy169@gamil.com
Classifier: Programming Language :: Python :: 3
Classifier: License :: OSI Approved :: MIT License
Classifier: Operating System :: OS Independent
Requires-Python: >=3.6
License-File: LICENSE
Requires-Dist: sumy
Requires-Dist: Pillow
Requires-Dist: schedule
Requires-Dist: sympy
Requires-Dist: requests
Dynamic: author
Dynamic: author-email
Dynamic: classifier
Dynamic: description
Dynamic: description-content-type
Dynamic: home-page
Dynamic: requires-dist
Dynamic: requires-python
Dynamic: summary
